korean_law_mcp/__init__.py
korean_law_mcp/api_client.py
korean_law_mcp/main.py
korean_law_mcp/prompts.py
korean_law_mcp/resources.py
korean_law_mcp/server.py
korean_law_mcp/tools.py
korean_law_mcp/utils.py
korean_law_mcp-0.4.4.dist-info/METADATA
korean_law_mcp-0.4.4.dist-info/WHEEL
korean_law_mcp-0.4.4.dist-info/entry_points.txt
korean_law_mcp-0.4.4.dist-info/licenses/LICENSE
korean_law_mcp-0.4.4.dist-info/RECORD
