Metadata-Version: 2.4
Name: korean-law-mcp
Version: 0.4.4
Summary: MCP Server for Korean Law Open API
Project-URL: Repository, https://github.com/seo-jinseok/korean-law-mcp
Author-email: Seo Jinseok <truestone@gmail.com>
License-Expression: MIT
License-File: LICENSE
Requires-Python: >=3.10
Requires-Dist: mcp[cli]>=0.1.0
Requires-Dist: python-dotenv>=1.0.0
Requires-Dist: requests>=2.31.0
Requires-Dist: xmltodict>=0.13.0
